sigfoxapiv2/__init__.py
sigfoxapiv2/helper.py
sigfoxapiv2-0.5.6.dist-info/METADATA
sigfoxapiv2-0.5.6.dist-info/WHEEL
sigfoxapiv2-0.5.6.dist-info/top_level.txt
sigfoxapiv2-0.5.6.dist-info/RECORD
