Metadata-Version: 2.1
Name: sigfoxapiv2
Version: 0.5.6
Summary: Python wrapper for the v2 Sigfox API
Home-page: https://github.com/barter4things/sigfoxapiv2
Author: Matthew Hopson
Author-email: matt.hopson@b4tgroup.co.uk
License: UNKNOWN
Platform: UNKNOWN
